flipdisc/__init__.py
flipdisc/_particle.abi3.so
flipdisc/binarize.cpython-37m-darwin.so
flipdisc/build_particle.py
flipdisc/image.py
flipdisc/optical_flow.py
flipdisc/particle.py
flipdisc/util.py
flipdisc/framework/__init__.py
flipdisc/framework/app.py
flipdisc/framework/common.py
flipdisc/framework/manifest.py
flipdisc/framework/red.py
flipdisc/framework/userapp.json
flipdisc-1.0.0.dist-info/METADATA
flipdisc-1.0.0.dist-info/WHEEL
flipdisc-1.0.0.dist-info/top_level.txt
flipdisc-1.0.0.dist-info/RECORD
