Metadata-Version: 2.1
Name: flipdisc
Version: 1.0.0
Home-page: https://github.com/breakfastny/flipdisc-python-framework
Requires-Python: >=3.7.*
Requires-Dist: cffi (==1.15.0)
Requires-Dist: numpy (==1.21.6)
Requires-Dist: jsonschema (==4.6.0)
Requires-Dist: pyzmq (==23.2.0)
Requires-Dist: redis (==4.3.3)
